{
  "dotfiles": 3,
  "cli": 1,
  "docker": 2,
  "containers": 1,
  "devops": 5,
  "sre": 1,
  "jenkins": 2,
  "pipeline": 2,
  "cicd": 3,
  "github-actions": 1,
  "deployment": 2,
  "microservices": 3,
  "module-federation": 1,
  "webpack": 1,
  "dx": 2,
  "developer-experience": 3,
  "productivity": 2,
  "cloud": 1,
  "cost": 1,
  "distro-hopping": 1,
  "developer-productivity": 5,
  "ricing": 1,
  "unix": 2,
  "linux": 2,
  "gnu-stow": 1,
  "neovim": 2,
  "ansible-playbook": 1,
  "lab": 1,
  "note-taking": 2,
  "shell-script": 1,
  "zsh": 1,
  "nodejs": 1,
  "obsidian": 1,
  "react": 1,
  "javascript": 1,
  "immer": 1,
  "design-patterns": 1,
  "hack": 1
}
